stock_analysis/__init__.py
stock_analysis/candle_gap_analysis.py
stock_analysis/chart_patterns.py
stock_analysis/fibonacci_levels.py
stock_analysis/ltp_near_gaps.py
stock_analysis/run_analysis.py
stock_analysis/stock_data_manager.py
stock_analysis/support_resistance.py
stock_analysis_yf-0.1.0.dist-info/METADATA
stock_analysis_yf-0.1.0.dist-info/WHEEL
stock_analysis_yf-0.1.0.dist-info/entry_points.txt
stock_analysis_yf-0.1.0.dist-info/top_level.txt
stock_analysis_yf-0.1.0.dist-info/RECORD
