Metadata-Version: 2.4
Name: stock-analysis-yf
Version: 0.1.0
Summary: A suite of stock analysis tools using yfinance
Author-email: Prasad <user@example.com>
Keywords: finance,trading,stock-analysis
Classifier: Programming Language :: Python :: 3
Classifier: License :: OSI Approved :: MIT License
Classifier: Operating System :: OS Independent
Requires-Python: >=3.8
Requires-Dist: yfinance
Requires-Dist: pandas
Requires-Dist: numpy
Requires-Dist: tqdm
Requires-Dist: matplotlib
Requires-Dist: mplfinance
Requires-Dist: prettytable
Requires-Dist: tabulate
Requires-Dist: scipy
